test/bus/fake_cpu.v
module mips_cpu_bus(
    /* Standard signals */
    input logic clk,
    input logic reset,
    output logic active,
    output logic[31:0] register_v0,

    /* Avalon memory mapped bus controller (master) */
    output logic[31:0] address,
    output logic write,
    output logic read,
    input logic waitrequest,
    output logic[31:0] writedata,
    output logic[3:0] byteenable,
    input logic[31:0] readdata
);


	initial begin
		// finished initial reset
		@(negedge reset);

		// slack
		@(negedge clk);
		@(negedge clk);

		// wait until ram is valid
		@(negedge waitrequest);
		read <= 0;
		write <= 1;
		address <= 32'h4;
		writedata <= 32'hAABBCCDD;
		byteenable <= 4'b1100;

		@(negedge waitrequest);
		read <= 0;
		write <= 1;
		address <= 32'h4;
		writedata <= 32'hFFFFCCDD;
		byteenable <= 4'b0011;
		
		@(negedge waitrequest);
		read <= 1;
		write <= 0;
		address <= 32'h4;
		writedata <= 32'hFFFFCCDD;
		byteenable <= 4'b1111;

		@(negedge waitrequest);
		read <= 0;
		write <= 1;
		address <= 32'h0;
		writedata <= 32'hFFFFCCDD;
		byteenable <= 4'b0010;


		#40;

		$finish;
	end


endmodule

test/bus/mips_cpu_bus_tb.v
module mips_cpu_bus_tb (
	output logic active,
    output logic[31:0] register_v0
);
	
	logic clk;
    logic reset;

    /* Avalon memory mapped bus controller (master) Controls */
    logic[31:0] address;
    logic write;
    logic read;
    logic waitrequest;
    logic[31:0] writedata;
    logic[3:0] byteenable;
    logic[31:0] readdata;

	// BUS CPU
	mips_cpu_bus dut(
		.clk(clk),
		.reset(reset),
		.active(active),
		.register_v0(register_v0),
		.address(address),
		.write(write),
		.read(read),
		.waitrequest(waitrequest),
		.writedata(writedata),
		.byteenable(byteenable),
		.readdata(readdata)
	);


    // CLK
    initial begin
        $dumpfile("mips_cpu_bus_tb.vcd");
        $dumpvars(0, mips_cpu_bus_tb);
        clk = 0;
        repeat (400) begin
            #2;
            clk = !clk;
        end
        $fatal(1, "Simulation ended in 200 clock cycles");
    end

	// RAM INIT
    parameter RAM_INIT_FILE = "";
    reg [31:0] ram [0:255];

	initial begin
        for(integer i = 0; i < 255; i=i+1) begin
            ram[i] = 0;
        end
        if (RAM_INIT_FILE != "") begin
            $display("RAM : INIT : Loading RAM contents from %s", RAM_INIT_FILE);
            $readmemb(RAM_INIT_FILE, ram);
        end
    end


	// RAM READ & WRITE
    logic[31:0] ram_write_data;
    logic[7:0] ram_wordaddr;
    logic[9:0] shift_tmp;

    assign shift_tmp = address[9:0] >> 2;
    assign ram_wordaddr = shift_tmp[7:0];

    // RAM DEBUG PEAK WIRES
    logic [31:0] ram_0, ram_4, ram_8, ram_12, ram_16;
    assign ram_0 = ram[0];
    assign ram_4 = ram[1];
    assign ram_8 = ram[2];
    assign ram_12 = ram[3];
    assign ram_16 = ram[4];

    // ram write byte masks
    always @(*) begin
        case(byteenable)
            4'b0000: ram_write_data = ram[ram_wordaddr];
            4'b0001: ram_write_data = { ram[ram_wordaddr][31:8], writedata[7:0] };
            4'b0010: ram_write_data = { ram[ram_wordaddr][31:16], writedata[15:8], ram[ram_wordaddr][7:0] };
            4'b0100: ram_write_data = { ram[ram_wordaddr][31:24], writedata[23:16], ram[ram_wordaddr][15:0] };
            4'b1000: ram_write_data = { writedata[31:24], ram[ram_wordaddr][23:0] };
            4'b0011: ram_write_data = { ram[ram_wordaddr][31:16], writedata[15:0] };
            4'b1100: ram_write_data = { writedata[31:16], ram[ram_wordaddr][15:0] };
            4'b1111: ram_write_data = writedata;
            default: ram_write_data = writedata;
        endcase
    end

    always_ff @(posedge clk) begin
        
        // if wait request not high, can process read/write 
        if(!waitrequest) begin
            if(read) begin
                readdata <= ram[ram_wordaddr];
            end

            if(write) begin
                ram[ram_wordaddr] <= ram_write_data;
            end
        end

        // random wait signal
        waitrequest = $random();

    end

    // TESTING
    initial begin
        $monitor("Time %t:\n[RAM] PC: %h, WordADDR: %h, Instruction: %h\n[CPU] Active: %d, Register_v0 ($2): %h",
                 $time, address, ram_wordaddr, readdata, active, register_v0);

        reset = 0;
        @(negedge clk);
        reset = 1;
        @(negedge clk);
        reset = 0;

        @(negedge active); // wait until cpu ends

    end


endmodule

test/bus/mips_cpu_bus_tb.vcd
$date
	Thu Dec  2 01:00:30 2021
$end
$version
	Icarus Verilog
$end
$timescale
	1s
$end
$scope module mips_cpu_bus_tb $end
$var wire 32 ! ram_0 [31:0] $end
$var wire 32 " ram_12 [31:0] $end
$var wire 32 # ram_16 [31:0] $end
$var wire 32 $ ram_4 [31:0] $end
$var wire 32 % ram_8 [31:0] $end
$var wire 32 & writedata [31:0] $end
$var wire 1 ' write $end
$var wire 10 ( shift_tmp [9:0] $end
$var wire 32 ) register_v0 [31:0] $end
$var wire 1 * read $end
$var wire 8 + ram_wordaddr [7:0] $end
$var wire 4 , byteenable [3:0] $end
$var wire 32 - address [31:0] $end
$var wire 1 . active $end
$var reg 1 / clk $end
$var reg 32 0 ram_write_data [31:0] $end
$var reg 32 1 readdata [31:0] $end
$var reg 1 2 reset $end
$var reg 1 3 waitrequest $end
$scope module dut $end
$var wire 1 / clk $end
$var wire 32 4 readdata [31:0] $end
$var wire 1 2 reset $end
$var wire 1 3 waitrequest $end
$var reg 1 . active $end
$var reg 32 5 address [31:0] $end
$var reg 4 6 byteenable [3:0] $end
$var reg 1 * read $end
$var reg 32 7 register_v0 [31:0] $end
$var reg 1 ' write $end
$var reg 32 8 writedata [31:0] $end
$upscope $end
$scope begin $ivl_for_loop0 $end
$var integer 32 9 i [31:0] $end
$upscope $end
$upscope $end
$enddefinitions $end
#0
$dumpvars
b11111111 9
bx 8
bx 7
bx 6
bx 5
bx 4
x3
02
bx 1
bx 0
0/
x.
bx -
bx ,
bx +
x*
bx )
b0xxxxxxxx (
x'
bx &
b0 %
b0 $
b0 #
b0 "
b0 !
$end
#2
03
1/
#4
12
0/
#6
13
1/
#8
02
0/
#10
1/
#12
0/
#14
1/
#16
0/
#18
1/
#20
0/
#22
1/
#24
0/
#26
1/
#28
0/
#30
b1 +
b1 (
b10101010101110110000000000000000 0
b1100 ,
b1100 6
b10101010101110111100110011011101 &
b10101010101110111100110011011101 8
b100 -
b100 5
1'
0*
03
1/
#32
0/
#34
b10101010101110110000000000000000 $
13
1/
#36
0/
#38
1/
#40
0/
#42
b10101010101110111100110011011101 0
b11 ,
b11 6
b11111111111111111100110011011101 &
b11111111111111111100110011011101 8
03
1/
#44
0/
#46
b10101010101110111100110011011101 $
13
1/
#48
0/
#50
1/
#52
0/
#54
b11111111111111111100110011011101 0
b1111 ,
b1111 6
0'
1*
03
1/
#56
0/
#58
b10101010101110111100110011011101 1
b10101010101110111100110011011101 4
13
1/
#60
0/
#62
b0 +
b0 (
b1100110000000000 0
b10 ,
b10 6
b0 -
b0 5
1'
0*
03
1/
#64
0/
#66
b1100110000000000 !
13
1/
#68
0/
#70
03
1/
#72
0/
#74
13
1/
#76
0/
#78
1/
#80
0/
#82
03
1/
#84
0/
#86
13
1/
#88
0/
#90
03
1/
