rtl/bus/controlpath/ir/ir.v
module ir(
	input logic[31:0] read_data,
    input logic stall,
    input logic clk,
    input logic state,
	output logic[5:0] instruction_opcode,
    output logic[31:0] instruction_word,
    output logic[4:0] rs, rd, rt,
    output logic[4:0] shamt,
    output logic[15:0] alu_immediate,
    output logic[5:0] func_code,
    output logic [4:0] special_branch_codes

);
    logic[31:0] ir_hold, ir_hold_next;
    logic stall_prev;
    
    always @(*) begin
        // muxed IW output
        instruction_word = (state & !stall_prev) ? read_data: ir_hold;

        // bit slicing operations
        instruction_opcode = instruction_word[31:26];
        rs = instruction_word[25:21];
        rt = instruction_word[20:16];
        rd = instruction_word[15:11];
        shamt = instruction_word[10:6];
        alu_immediate = instruction_word[15:0];
        func_code = instruction_word[5:0];
        special_branch_codes = instruction_word[20:16];
    end

    always_ff @(posedge clk) begin
        stall_prev <= stall;

        if(state & !stall_prev) begin // enable for ir_hold
            ir_hold <= read_data;  
        end
    end

endmodule

rtl/bus/controlpath/ir/ir_tb.v
module ir_tb();

    logic[31:0] read_data, instruction_word;
    logic stall, clk, state, reset;

    initial begin
        $dumpfile("ir_tb.vcd");
        $dumpvars(0, ir_tb);
        clk = 0;
        forever begin
            #2
            clk = !clk;
        end
    end

    logic state_next;
    assign state_next = (stall) ? state : !state;

    always_ff@(posedge clk) begin
        if(reset)
            state <= 0;
        else begin
            state <= state_next;
        end
    end

    initial begin
        reset = 0; stall = 0;
        @(posedge clk);
        reset = 1;
        @(negedge clk);
        reset = 0;
        
        @(posedge clk);
        read_data <= 32'hffffffff; // instruction
        @(posedge clk);
        read_data <= 32'h01; // data or garbage

        // add in stalls in exec
        //1 cycle stall
        @(posedge clk);
        read_data <= 32'hfffffffe; // instruction
        stall <= 1;
        @(posedge clk);
        stall <= 0;
        read_data <= 32'hx; // garbage
        @(posedge clk);

        // 2 cycle stall
        @(posedge clk);
        read_data <= 32'hfffffffd; // instruction
        stall <= 1;
        @(posedge clk);
        read_data <= 32'hx; // garbage
        @(posedge clk);
        stall <= 0;
        @(posedge clk);

        // add in stalls in fetch
        // 1 stall
        stall <= 1;
        @(posedge clk);
        stall <=0;


        @(posedge clk);
        read_data <= 32'h01; // data or garbage

        @(posedge state);
        read_data <= 32'hfffffffc; // instruction
        @(negedge state);
        read_data <= 32'h01; // data or garbage

        // 2 stalls
        stall <= 1;
        @(posedge clk);
        @(posedge clk);
        stall <=0;


        @(posedge clk);
        read_data <= 32'h01; // data or garbage

        @(posedge state);
        read_data <= 32'hfffffffb; // instruction
        @(negedge state);
        read_data <= 32'h01; // data or garbage
        @(posedge state);

        $finish;
    end



    ir dut(
        .read_data(read_data),
        .stall(stall),
        .clk(clk),
        .state(state),
        .instruction_word(instruction_word)
    );
endmodule

rtl/bus/controlpath/ir/ir_tb.vcd
$date
	Thu Dec  2 00:38:35 2021
$end
$version
	Icarus Verilog
$end
$timescale
	1s
$end
$scope module ir_tb $end
$var wire 1 ! state_next $end
$var wire 32 " instruction_word [31:0] $end
$var reg 1 # clk $end
$var reg 32 $ read_data [31:0] $end
$var reg 1 % reset $end
$var reg 1 & stall $end
$var reg 1 ' state $end
$scope module dut $end
$var wire 1 # clk $end
$var wire 32 ( read_data [31:0] $end
$var wire 1 & stall $end
$var wire 1 ' state $end
$var reg 16 ) alu_immediate [15:0] $end
$var reg 6 * func_code [5:0] $end
$var reg 6 + instruction_opcode [5:0] $end
$var reg 32 , instruction_word [31:0] $end
$var reg 32 - ir_hold [31:0] $end
$var reg 32 . ir_hold_next [31:0] $end
$var reg 5 / rd [4:0] $end
$var reg 5 0 rs [4:0] $end
$var reg 5 1 rt [4:0] $end
$var reg 5 2 shamt [4:0] $end
$var reg 5 3 special_branch_codes [4:0] $end
$var reg 1 4 stall_prev $end
$upscope $end
$upscope $end
$enddefinitions $end
#0
$dumpvars
x4
bx 3
bx 2
bx 1
bx 0
bx /
bx .
bx -
bx ,
bx +
bx *
bx )
bx (
x'
0&
0%
bx $
0#
bx "
x!
$end
#2
1!
04
0'
1%
1#
#4
0%
0#
#6
0!
b11111 3
b111111 *
b1111111111111111 )
b11111 2
b11111 /
b11111 1
b11111 0
b111111 +
b11111111111111111111111111111111 .
b11111111111111111111111111111111 "
b11111111111111111111111111111111 ,
1'
b11111111111111111111111111111111 $
b11111111111111111111111111111111 (
1#
#8
0#
#10
1!
b1 $
b1 (
b11111111111111111111111111111111 -
0'
1#
#12
0#
#14
b111110 *
b1111111111111110 )
b11111111111111111111111111111110 .
b11111111111111111111111111111110 "
b11111111111111111111111111111110 ,
1'
1&
b11111111111111111111111111111110 $
b11111111111111111111111111111110 (
1#
#16
0#
#18
0!
bx $
bx (
0&
b11111111111111111111111111111110 -
14
1#
#20
0#
#22
1!
0'
04
1#
#24
0#
#26
b111101 *
b1111111111111101 )
b11111111111111111111111111111101 .
b11111111111111111111111111111101 "
b11111111111111111111111111111101 ,
1&
b11111111111111111111111111111101 $
b11111111111111111111111111111101 (
1'
1#
#28
0#
#30
b11111111111111111111111111111101 -
14
bx $
bx (
1#
#32
0#
#34
0!
0&
1#
#36
0#
#38
0'
04
1&
1#
#40
0#
#42
1!
0&
14
1#
#44
0#
#46
0!
b11111 3
b111100 *
b1111111111111100 )
b11111 2
b11111 /
b11111 1
b11111 0
b111111 +
b11111111111111111111111111111100 .
b11111111111111111111111111111100 "
b11111111111111111111111111111100 ,
1'
04
b11111111111111111111111111111100 $
b11111111111111111111111111111100 (
1#
#48
0#
#50
1&
b1 $
b1 (
0!
b11111111111111111111111111111100 -
0'
1#
#52
0#
#54
14
1#
#56
0#
#58
1!
0&
1#
#60
0#
#62
b11111111111111111111111111111011 $
b11111111111111111111111111111011 (
0!
b11111 3
b111011 *
b1111111111111011 )
b11111 2
b11111 /
b11111 1
b11111 0
b111111 +
b11111111111111111111111111111011 .
b11111111111111111111111111111011 "
b11111111111111111111111111111011 ,
1'
04
1#
#64
0#
#66
b1 $
b1 (
1!
b11111111111111111111111111111011 -
0'
1#
#68
0#
#70
0!
b0 3
b1 *
b1 )
b0 2
b0 /
b0 1
b0 0
b0 +
b1 .
b1 "
b1 ,
1'
1#
