rtl/harvard-5-instr/alu.v
// only ADDU, ADDIU instructions

module alu(
	input logic[31:0] op1, op2,
	input logic[5:0] ALUOp,
	input logic[5:0] func_code,
	output logic[31:0] alu_out
);
	logic[11:0] alu_control; // concatenation of opcode and function code

	always_comb begin
		if(ALUOp == 6'b000000) begin
			if(func_code == 6'b100001)
				alu_out = op1 + op2; // ADDU
				alu_out = op1 + op2; // JR
		end
		else begin
			casex (ALUOp)
				6'b001001: alu_out = op1 + op2; // ADDIU
				6'b100011: alu_out = op1 + op2; // LW
				6'b101011: alu_out = op1 + op2; // SW
				default: alu_out = 32'hxxxxxxxx;
			endcase
		end

		// alu_control = {ALUOp, func_code};
		// casex (alu_control)
		// 	(12'b000000100001 || 12'b001001??????): alu_out = op1 + op2;
		// 	default: alu_out = 12'hxxx;
		// endcase
	end
	
endmodule

rtl/harvard-5-instr/regfile.v
module regfile (
	input logic clk, wen, reset,
	input logic[31:0] write_data,
	input logic[4:0] write_addr,
	input logic[4:0] read_addr_0, read_addr_1,
	output logic[31:0] read_data_0, read_data_1
);

	reg [31:0] regs [31:0];

	always_ff @(posedge clk) begin
		if(reset == 1) begin
			for(integer i = 0; i < 32; i=i+1) begin
				regs[i] <= 0;
			end
		end
		if(wen == 1) begin
			regs[write_addr] = (write_addr == 0) ? 0 : write_data;
		end
	end

	always_comb begin
		read_data_0 = (read_addr_0 == 0) ? 0 : regs[read_addr_0];
		read_data_1 = (read_addr_1 == 0) ? 0 : regs[read_addr_1];
	end

endmodule

rtl/harvard-5-instr/datapath.v
module datapath(
	input logic clk, reset,
	input logic RegDst, MemtoReg,ALUSrc,RegWrite,
	input logic[4:0] rs, rt, rd,
    input logic[5:0] func_code,ALUOp,
	input logic[15:0] alu_immediate,
	input logic[31:0] data_readdata,
	output logic[31:0] data_address, data_writedata, reg_read_data_0
);

	// REGFILE INPUTS
	logic[31:0] reg_write_data;
	logic[4:0] reg_write_addr;
	logic[4:0] reg_read_addr_0, reg_read_addr_1;

	// REGFILE OUTPUTS
	logic[31:0] reg_read_data_1;

	assign reg_read_addr_0 = rs;
	assign reg_read_addr_1 = rt;
	assign reg_write_addr = (RegDst) ? rt : rd;


	//REGFILE
	regfile regfile_0(
		.clk(clk), .wen(RegWrite), .reset(reset),
		.write_data(reg_write_data), .write_addr(reg_write_addr),
		.read_addr_0(reg_read_addr_0), .read_addr_1(reg_read_addr_1),
		.read_data_0(reg_read_data_0), .read_data_1(reg_read_data_1)
	);

	logic [31:0] sign_extended;
	assign sign_extended = (alu_immediate[15]) ? {16'hffff, alu_immediate} : {16'h0000, alu_immediate};

	//ALU
	logic add;
	logic[31:0] alu_out;
	logic[31:0] op2;
	assign op2 = (ALUSrc) ? sign_extended : reg_read_data_1;
	alu alu_0(
		.op1(reg_read_data_0),
		.op2(op2),
		.ALUOp(ALUOp),
		.func_code(func_code),
		.alu_out(alu_out)
	);

	// WRAP AROUND RAM
	assign data_address = alu_out;
	assign data_writedata = reg_read_data_1;
	
	assign reg_write_data = (MemtoReg) ? data_readdata : alu_out;  



	
endmodule

rtl/harvard-5-instr/control.v
module control ( 
    input logic [5:0] instruction_opcode,
    input logic [5:0] func_code,
    output logic RegDst,
    output logic Branch,
    output logic MemRead,
    output logic MemtoReg,
    output logic [5:0] ALUOp,
    output logic MemWrite,
    output logic ALUSrc,
    output logic RegWrite
);

    always_comb begin
        ALUOp = instruction_opcode;
        if (instruction_opcode == 0) begin
            RegDst = 1;
            Branch = (func_code == 6'b001000) ? 1 : 0;
            MemRead = 0;
            MemtoReg = 0;
            //ALUOp = 1;
            MemWrite = 0;
            ALUSrc = 0;
            RegWrite = 1;
        end
        else if (instruction_opcode == 6'b00001?) begin
            RegDst = 0;
            Branch = 1;
            MemRead = 0;
            MemtoReg = 0;
            //ALUOp = 0;
            MemWrite = 0;
            ALUSrc = 0;
            RegWrite = 0;

        end
        else begin
            RegDst = 1;
            Branch = 0;
            if (instruction_opcode == 12) begin
                MemRead = 0;
                MemtoReg = 0;
                //ALUOp = 1;
                MemWrite = 0;
                ALUSrc = 1;
                RegWrite = 1;
            end
            else if (instruction_opcode == 6'h23) begin
                MemRead = 1;
                MemtoReg = 1;
                //ALUOp = 1;
                MemWrite = 0;
                ALUSrc = 1;
                RegWrite = 1;
                
            end
            else begin
                MemRead = 0;
                MemtoReg = 0;
                // = 1;
                MemWrite = 0;
                ALUSrc = 1;
                RegWrite = 0;
            end
        end
        
    end
endmodule

rtl/harvard-5-instr/pc.v
module pc (
	input logic immediate, // goes high when immediate address required
	input logic [31:0] Rd, //register content for immediate addressing
	input logic clk, reset, //clock & reset
	output logic [31:0] addr //the output address
);

	logic [31:0] addr_next;

	assign addr_next = (immediate) ? Rd : addr + 4;

	always_ff @(posedge clk) begin
		if(reset) begin
			addr <= 32'hBFC00000;
		end else begin
			addr <= addr_next;		
		end
	end


endmodule

rtl/harvard-5-instr/ir.v
module ir(
	input logic[31:0] read_data,
	output logic[5:0] instruction_opcode,
    output logic[31:0] instruction_word,
    output logic[4:0] rs, rd, rt,
    output logic[15:0] alu_immediate,
    output logic[5:0] func_code

);
    always @(*) begin
        instruction_opcode = read_data[31:26];
        instruction_word = read_data; // need to change for bus interface, add mux and IR reg
        rs = instruction_word[25:21];
        rt = instruction_word[20:16];
        alu_immediate = instruction_word[15:0];
        func_code = instruction_word[5:0];

        // if (instruction_opcode == 0) begin
        //     func_code = instruction_word[5:0];
        // end else begin
        //     func_code = 6'bxxxxxx;
        // end
    end

endmodule

rtl/harvard-5-instr/controlpath.v
module controlpath (
	input logic[31:0] instr_read_data, // from memory bus
	input logic[31:0] reg_read_data_0, // from regfile for JR
	input logic clk, reset,
	output logic[15:0] alu_immediate,
	output logic[4:0] rs, rd, rt,
	output logic RegDst,
	output logic Branch,
	output logic MemtoReg,
	output logic[5:0] ALUOp,
	output logic ALUSrc,
	output logic RegWrite,
	output logic[31:0] instr_read_addr,
    output logic[5:0] func_code,
	output logic data_read, data_write
);

	logic[31:0] instruction_word;
	logic[5:0] instruction_opcode;

	ir irblock(
		.read_data(instr_read_data), //input
		.instruction_opcode(instruction_opcode), //output
		.instruction_word(instruction_word), //output
		.rs(rs), //output
		.rd(rd), //output
		.rt(rt), //output
		.alu_immediate(alu_immediate), //output
		.func_code(func_code) //output
	);

	pc pcblock(
		.reset(reset),
		.immediate(Branch), // PROB A BUG HERE... more logic may be needed within PC block; input
		.Rd(reg_read_data_0), //register content for immediate addressing; input
		.clk(clk), //clock; input
		.addr(instr_read_addr) //the output address; output
	);

	control controlblock(
		.instruction_opcode(instruction_opcode), //input
		.RegDst(RegDst), //output
		.Branch(Branch), //output
		.MemRead(data_read), //output
		.MemtoReg(MemtoReg), //output
		.ALUOp(ALUOp), //output
		.MemWrite(data_write), //output
		.ALUSrc(ALUSrc), //output
		.RegWrite(RegWrite) //output
	);
endmodule

rtl/harvard-5-instr/mips_cpu_harvard.v
module mips_cpu_harvard(
    /* Standard signals */
    input logic     clk,
    input logic     reset,
    output logic    active, //not implemented yet
    output logic [31:0] register_v0, //not implemented yet

    /* New clock enable. See below. */
    input logic     clk_enable, //not implemented yet

    /* Combinatorial read access to instructions */
    output logic[31:0]  instr_address,
    input logic[31:0]   instr_readdata,

    /* Combinatorial read and single-cycle write access to instructions */
    output logic[31:0]  data_address,
    output logic        data_write,
    output logic        data_read,
    output logic[31:0]  data_writedata,
    input logic[31:0]  data_readdata
);
    //intermediate signals
    logic[4:0] rs, rt, rd;
    logic RegDst, Branch, MemtoReg, ALUSrc, RegWrite;
    logic[15:0] alu_immediate;
    logic[31:0] reg_read_data_0;
    logic[5:0] func_code, ALUOp;

    // Control Path
    controlpath controlpathblock(
        .instr_read_data(instr_readdata), //input 
        .reg_read_data_0(reg_read_data_0), //input 
        .clk(clk), .reset(reset),//input
        .alu_immediate(alu_immediate),//output
        .rs(rs), //output
        .rd(rd), //output
        .rt(rt),//output
	    .RegDst(RegDst),//output
	    .Branch(Branch),//output
	    .MemtoReg(MemtoReg),//output
	    .ALUOp(ALUOp),//output
	    .ALUSrc(ALUSrc),//output
	    .RegWrite(RegWrite),//output
	    .instr_read_addr(instr_address),//output   
        .func_code(func_code),//output
	    .data_read(data_read),//output  
        .data_write(data_write)//output  
    );

    // Data Path
    datapath datapathblock(
        .clk(clk), //input
        .reset(reset),//input
        .RegDst(RegDst), //input
        .MemtoReg(MemtoReg),//input
        .ALUSrc(ALUSrc),//input
        .RegWrite(RegWrite),//input
        .rs(rs), //input
        .rt(rt), //input
        .rd(rd),//input
        .alu_immediate(alu_immediate),//input
        .data_readdata(data_readdata),//input
        .func_code(func_code), //input
        .ALUOp(ALUOp),//input
        .data_address(data_address), //output
        .data_writedata(data_writedata), //output
        .reg_read_data_0(reg_read_data_0)//output
    );

// BFC0 0000
//         |
// BFC0 00FF
// reg [31:0] ram [0:4294967296 - 1]; this is what we want

// reg [31:0] ram [0:255]; this is what we have at home



endmodule

rtl/harvard-5-instr/mips_cpu_harvard_tb.v
module mips_cpu_harvard_tb();

    logic clk;
    logic reset;
    logic active;
    logic [31:0] register_v0;

    /* New clock enable. See below. */
    logic clk_enable; /* Combinatorial read access to instructions */
    logic[31:0] instr_address;
    logic[31:0] instr_readdata;

    /* Combinatorial read and single-cycle write access to instructions */
    logic[31:0] data_address;
    logic data_write;
    logic data_read;
    logic[31:0] data_writedata;
    logic[31:0] data_readdata;

    logic [31:0] instruction_word;
    logic [31:0] source_register_1_data;
    logic [31:0] source_register_2_data;
    logic [31:0] destination_register_data;
    

    mips_cpu_harvard dut(
        .clk(clk),
        .reset(reset),
        .active(active),
        .register_v0(register_v0),
        .clk_enable(clk_enable),
        .instr_address(instr_address),
        .instr_readdata(instr_readdata),
        .data_address(data_address),
        .data_write(data_write),
        .data_read(data_read),
        .data_writedata(data_writedata),
        .data_readdata(data_readdata)
    );
    
    initial begin
        $dumpfile("mips_cpu_harvard_tb.vcd");
        $dumpvars(0, mips_cpu_harvard_tb);
        clk = 0;
        repeat (200) begin
            #2;
            clk = !clk;
        end
        $fatal(2, "Simulation ended in 100 clock cycles");
    end

    reg [31:0] rom [0:255];
    reg [31:0] ram [0:255];

    parameter ROM_INIT_FILE = "test0_rom.mem";
    parameter RAM_INIT_FILE = "test1_ram.mem";

    // RAM ROM initialisation
    initial begin
        for(integer i = 0; i < 255; i=i+1) begin
            rom[i] = 0;
            ram[i] = 0;
        end

        if (ROM_INIT_FILE != "") begin
            $display("ROM : INIT : Loading RAM contents from %s", ROM_INIT_FILE);
            $readmemb(ROM_INIT_FILE, rom);
        end

        if (RAM_INIT_FILE != "") begin
            $display("RAM : INIT : Loading RAM contents from %s", RAM_INIT_FILE);
            $readmemh(RAM_INIT_FILE, ram);
        end
    end

    // ROM and RAM READ
    logic [7:0] rom_wordaddr, ram_wordaddr;
    assign rom_wordaddr = instr_address[7:0] >> 2;
    assign ram_wordaddr = data_address[7:0] >> 2;

    assign instr_readdata = (instr_address[31:8] == 24'hBFC000) ? rom[rom_wordaddr] : 32'hxxxxxxxx;
    assign data_readdata = (data_read && data_address[31:8] == 24'h000000) ? ram[ram_wordaddr] : 32'hxxxxxxxx;

    // RAM WRITE
    always_ff @(posedge clk) begin
        if(data_write && data_address[31:8] == 24'h000000) begin
            ram[data_address[7:0]] <= data_writedata;
        end
    end

    // TESTING
    initial begin
        reset = 0;
        $monitor("[ROM] PC: %h, WordADDR: %h, Instruction: %h", instr_address, rom_wordaddr, instr_readdata);
        @(negedge clk);
        reset = 1;
        @(negedge clk);
        reset = 0;
        @(negedge clk);

        #20;

        $finish;
    end


    // initial begin
    //     // instruction_word = 32'b00100101010000100000000001000101;
    //     @(posedge clk) begin
    //         repeat(10) begin
    //             #1;
    //             assert (destination_register_data == source_register_1_data + instruction_word[15:0]);
    //             instruction_word[15:0] += 16'h1235;
    //         end
    //     end
    // end

endmodule

rtl/harvard-5-instr/mips_cpu_harvard_tb.vcd
$date
	Sat Nov 20 18:11:25 2021
$end
$version
	Icarus Verilog
$end
$timescale
	1s
$end
$scope module mips_cpu_harvard_tb $end
$var wire 8 ! rom_wordaddr [7:0] $end
$var wire 32 " register_v0 [31:0] $end
$var wire 8 # ram_wordaddr [7:0] $end
$var wire 32 $ instr_readdata [31:0] $end
$var wire 32 % instr_address [31:0] $end
$var wire 32 & data_writedata [31:0] $end
$var wire 1 ' data_write $end
$var wire 32 ( data_readdata [31:0] $end
$var wire 1 ) data_read $end
$var wire 32 * data_address [31:0] $end
$var wire 1 + active $end
$var reg 1 , clk $end
$var reg 1 - clk_enable $end
$var reg 1 . reset $end
$scope module dut $end
$var wire 1 , clk $end
$var wire 1 - clk_enable $end
$var wire 32 / data_readdata [31:0] $end
$var wire 32 0 instr_readdata [31:0] $end
$var wire 1 . reset $end
$var wire 5 1 rt [4:0] $end
$var wire 5 2 rs [4:0] $end
$var wire 32 3 reg_read_data_0 [31:0] $end
$var wire 5 4 rd [4:0] $end
$var wire 32 5 instr_address [31:0] $end
$var wire 6 6 func_code [5:0] $end
$var wire 32 7 data_writedata [31:0] $end
$var wire 1 ' data_write $end
$var wire 1 ) data_read $end
$var wire 32 8 data_address [31:0] $end
$var wire 16 9 alu_immediate [15:0] $end
$var wire 1 : RegWrite $end
$var wire 1 ; RegDst $end
$var wire 1 < MemtoReg $end
$var wire 1 = Branch $end
$var wire 1 > ALUSrc $end
$var wire 6 ? ALUOp [5:0] $end
$var reg 1 + active $end
$var reg 32 @ register_v0 [31:0] $end
$scope module controlpathblock $end
$var wire 1 , clk $end
$var wire 32 A instr_read_data [31:0] $end
$var wire 1 . reset $end
$var wire 5 B rt [4:0] $end
$var wire 5 C rs [4:0] $end
$var wire 32 D reg_read_data_0 [31:0] $end
$var wire 5 E rd [4:0] $end
$var wire 32 F instruction_word [31:0] $end
$var wire 6 G instruction_opcode [5:0] $end
$var wire 32 H instr_read_addr [31:0] $end
$var wire 6 I func_code [5:0] $end
$var wire 1 ' data_write $end
$var wire 1 ) data_read $end
$var wire 16 J alu_immediate [15:0] $end
$var wire 1 : RegWrite $end
$var wire 1 ; RegDst $end
$var wire 1 < MemtoReg $end
$var wire 1 = Branch $end
$var wire 1 > ALUSrc $end
$var wire 6 K ALUOp [5:0] $end
$scope module controlblock $end
$var wire 6 L instruction_opcode [5:0] $end
$var wire 6 M func_code [5:0] $end
$var reg 6 N ALUOp [5:0] $end
$var reg 1 > ALUSrc $end
$var reg 1 = Branch $end
$var reg 1 ) MemRead $end
$var reg 1 ' MemWrite $end
$var reg 1 < MemtoReg $end
$var reg 1 ; RegDst $end
$var reg 1 : RegWrite $end
$upscope $end
$scope module irblock $end
$var wire 32 O read_data [31:0] $end
$var reg 16 P alu_immediate [15:0] $end
$var reg 6 Q func_code [5:0] $end
$var reg 6 R instruction_opcode [5:0] $end
$var reg 32 S instruction_word [31:0] $end
$var reg 5 T rd [4:0] $end
$var reg 5 U rs [4:0] $end
$var reg 5 V rt [4:0] $end
$upscope $end
$scope module pcblock $end
$var wire 1 , clk $end
$var wire 1 = immediate $end
$var wire 1 . reset $end
$var wire 32 W addr_next [31:0] $end
$var wire 32 X Rd [31:0] $end
$var reg 32 Y addr [31:0] $end
$upscope $end
$upscope $end
$scope module datapathblock $end
$var wire 6 Z ALUOp [5:0] $end
$var wire 1 > ALUSrc $end
$var wire 1 < MemtoReg $end
$var wire 1 ; RegDst $end
$var wire 1 : RegWrite $end
$var wire 16 [ alu_immediate [15:0] $end
$var wire 1 , clk $end
$var wire 32 \ data_address [31:0] $end
$var wire 32 ] data_readdata [31:0] $end
$var wire 32 ^ data_writedata [31:0] $end
$var wire 6 _ func_code [5:0] $end
$var wire 5 ` rd [4:0] $end
$var wire 5 a reg_read_addr_0 [4:0] $end
$var wire 5 b reg_read_addr_1 [4:0] $end
$var wire 1 . reset $end
$var wire 5 c rs [4:0] $end
$var wire 5 d rt [4:0] $end
$var wire 32 e sign_extended [31:0] $end
$var wire 32 f reg_write_data [31:0] $end
$var wire 5 g reg_write_addr [4:0] $end
$var wire 32 h reg_read_data_1 [31:0] $end
$var wire 32 i reg_read_data_0 [31:0] $end
$var wire 32 j op2 [31:0] $end
$var wire 32 k alu_out [31:0] $end
$scope module alu_0 $end
$var wire 6 l ALUOp [5:0] $end
$var wire 6 m func_code [5:0] $end
$var wire 32 n op2 [31:0] $end
$var wire 32 o op1 [31:0] $end
$var reg 12 p alu_control [11:0] $end
$var reg 32 q alu_out [31:0] $end
$upscope $end
$scope module regfile_0 $end
$var wire 1 , clk $end
$var wire 5 r read_addr_0 [4:0] $end
$var wire 5 s read_addr_1 [4:0] $end
$var wire 1 . reset $end
$var wire 1 : wen $end
$var wire 5 t write_addr [4:0] $end
$var wire 32 u write_data [31:0] $end
$var reg 32 v read_data_0 [31:0] $end
$var reg 32 w read_data_1 [31:0] $end
$scope begin $ivl_for_loop1 $end
$var integer 32 x i [31:0] $end
$upscope $end
$upscope $end
$upscope $end
$upscope $end
$scope begin $ivl_for_loop0 $end
$var integer 32 y i [31:0] $end
$upscope $end
$upscope $end
$enddefinitions $end
#0
$dumpvars
b11111111 y
bx x
bx w
bx v
bx u
bx t
bx s
bx r
bx q
bx p
bx o
bx n
bx m
bx l
bx k
bx j
bx i
bx h
bx g
bx f
bx e
bx d
bx c
bx b
bx a
bx `
bx _
bx ^
bx ]
bx \
bx [
bx Z
bx Y
bx X
bx W
bx V
bx U
bx T
bx S
bx R
bx Q
bx P
bx O
bx N
bx M
bx L
bx K
bx J
bx I
bx H
bx G
bx F
bx E
bx D
bx C
bx B
bx A
bx @
bx ?
1>
0=
0<
1;
0:
bx 9
bx 8
bx 7
bx 6
bx 5
bx 4
bx 3
bx 2
bx 1
bx 0
bx /
0.
x-
0,
x+
bx *
0)
bx (
0'
bx &
bx %
bx $
b0xxxxxx #
bx "
b0xxxxxx !
$end
#2
1,
#4
1.
0,
#6
b0 j
b0 n
b0xxxxxxxxxxxx *
b0xxxxxxxxxxxx 8
b0xxxxxxxxxxxx \
b0xxxxxxxxxxxx k
b0xxxxxxxxxxxx q
b100011000100 p
b100 e
b0 &
b0 7
b0 ^
b0 h
b0 w
b0 3
b0 D
b0 X
b0 i
b0 o
b0 v
1:
1<
1)
b100011 ?
b100011 K
b100011 N
b100011 Z
b100011 l
b100 6
b100 I
b100 M
b100 Q
b100 _
b100 m
b100 9
b100 J
b100 P
b100 [
b1 b
b1 s
b1 1
b1 B
b1 V
b1 d
b0 a
b0 r
b0 2
b0 C
b0 U
b0 c
b10001100000000010000000000000100 F
b10001100000000010000000000000100 S
b100011 G
b100011 L
b100011 R
b10001100000000010000000000000100 $
b10001100000000010000000000000100 0
b10001100000000010000000000000100 A
b10001100000000010000000000000100 O
b0 !
b10111111110000000000000000000100 W
b10111111110000000000000000000000 %
b10111111110000000000000000000000 5
b10111111110000000000000000000000 H
b10111111110000000000000000000000 Y
b100000 x
1,
#8
0.
0,
#10
b100011001000 p
b1000 e
b1000 6
b1000 I
b1000 M
b1000 Q
b1000 _
b1000 m
b1000 9
b1000 J
b1000 P
b1000 [
b10 b
b10 s
b10 1
b10 B
b10 V
b10 d
b10001100000000100000000000001000 F
b10001100000000100000000000001000 S
b10001100000000100000000000001000 $
b10001100000000100000000000001000 0
b10001100000000100000000000001000 A
b10001100000000100000000000001000 O
b1 !
b10111111110000000000000000001000 W
b10111111110000000000000000000100 %
b10111111110000000000000000000100 5
b10111111110000000000000000000100 H
b10111111110000000000000000000100 Y
1,
#12
0,
#14
b0xxxxxxxxxxxx f
b0xxxxxxxxxxxx u
b1001000011 p
b11 e
0:
0<
0)
b1001 ?
b1001 K
b1001 N
b1001 Z
b1001 l
b11 6
b11 I
b11 M
b11 Q
b11 _
b11 m
b11 9
b11 J
b11 P
b11 [
b11 b
b11 s
b11 1
b11 B
b11 V
b11 d
b1 a
b1 r
b1 2
b1 C
b1 U
b1 c
b100100001000110000000000000011 F
b100100001000110000000000000011 S
b1001 G
b1001 L
b1001 R
b100100001000110000000000000011 $
b100100001000110000000000000011 0
b100100001000110000000000000011 A
b100100001000110000000000000011 O
b10 !
b10111111110000000000000000001100 W
b10111111110000000000000000001000 %
b10111111110000000000000000001000 5
b10111111110000000000000000001000 H
b10111111110000000000000000001000 Y
1,
#16
0,
#18
b1100000100001 j
b1100000100001 n
b100001 p
b1100000100001 e
1:
0>
b0 ?
b0 K
b0 N
b0 Z
b0 l
b100001 6
b100001 I
b100001 M
b100001 Q
b100001 _
b100001 m
b1100000100001 9
b1100000100001 J
b1100000100001 P
b1100000100001 [
b10 a
b10 r
b10 2
b10 C
b10 U
b10 c
b10000110001100000100001 F
b10000110001100000100001 S
b0 G
b0 L
b0 R
b10000110001100000100001 $
b10000110001100000100001 0
b10000110001100000100001 A
b10000110001100000100001 O
b11 !
b10111111110000000000000000010000 W
b10111111110000000000000000001100 %
b10111111110000000000000000001100 5
b10111111110000000000000000001100 H
b10111111110000000000000000001100 Y
1,
#20
0,
#22
b100 !
b10111111110000000000000000010100 W
b10111111110000000000000000010000 %
b10111111110000000000000000010000 5
b10111111110000000000000000010000 H
b10111111110000000000000000010000 Y
1,
#24
0,
#26
b101 !
b10111111110000000000000000011000 W
b10111111110000000000000000010100 %
b10111111110000000000000000010100 5
b10111111110000000000000000010100 H
b10111111110000000000000000010100 Y
1,
#28
0,
#30
b110 !
b10111111110000000000000000011100 W
b10111111110000000000000000011000 %
b10111111110000000000000000011000 5
b10111111110000000000000000011000 H
b10111111110000000000000000011000 Y
1,
