rtl/harvard/controlpath/pc/branch_control.v
/* 
    This module decides whether a branch/jump should be executed or not.

    There are 12 branch/jump instructions in total.

    New control logic [1:0] jump_addr_selection is defined as such
        if 00: no jump;
        if 01: absolute jump (JR,JALR);
        if 10: page absolute jump (J,JAL);
        if 11: pc relative branch (all branch instructions);

    Written by JF
*/

module branch_control(
    input logic N, // high if alu_out is negative
    input logic Z, // high if alu_out is zero
    input logic[31:0] instruction_word, //taking in the entire word bc of repeated branch opcodes like JALR,JR,BGEZ,BGEZAL,BLTZ,BLTZAL
    // input logic R31, //taken from control.v; high for link instructions; not needed actually
    input logic state,
    input logic clk,

    // output logic Branch, // high if we want the PC to jump in the next fetch
    output logic B_link, // high if we want the PC+8 addr to be stored in $31
    output logic [1:0] jump_addr_selection // defined above
);

    logic[1:0] jump_addr_selection_next;

    always @(*) begin
        case (instruction_word[31:26]) // opcodes
            0: begin
                if (instruction_word[5:0] == 6'b001001) begin // JALR
                    jump_addr_selection_next = 2'b01; B_link = 1; 
                end
                else if (instruction_word[5:0] == 6'b001000) begin // JR
                    jump_addr_selection_next = 2'b01; B_link = 0; 
                end
                else begin
                    jump_addr_selection_next = 0; B_link = 0;
                end
            end
            6'b000001: begin // special_branch_codes case
                if (instruction_word[20:16] == 5'b00001) begin // BGEZ; assume ALU does either rs - 0 or rs + 0; branch if rs >= 0
                    jump_addr_selection_next = (!N | Z) ? 2'b11 : 0; 
                    B_link = 0;
                end
                else if (instruction_word[20:16] == 5'b10001) begin // BGEZAL; branch if rs >= 0
                    jump_addr_selection_next = (!N | Z) ? 2'b11 : 0; 
                    B_link = (!N | Z) ? 1 : 0;
                end
                else if (instruction_word[20:16] == 0) begin // BLTZ; branch if rs < 0
                    jump_addr_selection_next = (N) ? 2'b11 : 0;
                    B_link = 0;
                end
                else if (instruction_word[20:16] == 5'b10000) begin // BLTZAL; branch if rs < 0
                    jump_addr_selection_next = (N) ? 2'b11 : 0;
                    B_link = (N) ? 1 : 0;;
                end
                else begin
                    jump_addr_selection_next = 0; B_link = 0;
                end
            end
            6'b000010: begin // J
                jump_addr_selection_next = 2'b10; B_link = 0;
            end
            6'b000011: begin // JAL
                jump_addr_selection_next = 2'b10; B_link = 1;
            end
            6'b000100: begin // BEQ; assume alu does rs - rt; branch if rs==rt
                jump_addr_selection_next = (Z) ? 2'b11 : 0;
                B_link = 0;
            end
            6'b000101: begin // BNE; branch if rs!=rt
                jump_addr_selection_next = (!Z) ? 2'b11 : 0;
                B_link = 0;
            end
            6'b000110: begin // BLEZ; branch if rs <= 0
                jump_addr_selection_next = (N | Z) ? 2'b11 : 0;
                B_link = 0;
            end
            6'b000101: begin // BGTZ; branch if rs > 0
                jump_addr_selection_next = (!N) ? 2'b11 : 0;
                B_link = 0;
            end
        default: begin // otherwise, dont jump
            jump_addr_selection_next = 0; B_link = 0;
        end
        endcase
    end

    // at every EXEC, update FF
    // delay needed so that PC only jumps after branch delay slot
    // still bugged altho jump_addr_selection is correct now
    logic [31:0] tmp;
    always_ff @(posedge clk) begin
        if (state) begin
            jump_addr_selection <= tmp;
            tmp <= jump_addr_selection_next;
        end else begin
            jump_addr_selection <= jump_addr_selection;
        end
    end
endmodule

rtl/harvard/controlpath/pc/pc.v
/*
    Written by JF
*/

module pc(
    input logic clk,
    input logic state,
    input logic reset,
    input logic N, Z,
    input logic [31:0] instruction_word,
    input logic [31:0] read_data_0, // register data for JR, JALR

    output logic B_link, // bubbled up from branch_control.v so that control.v can make use of it in controlpath.v
    output logic [31:0] addr,
    output logic finish // goes high when trying to execute instruction address 0
);

    logic [31:0] addr_next, instruction_word_prev;
    logic [1:0] jump_addr_selection; // control signal defined in branch_control.v
    
    always @(*) begin
        if(addr == 0) begin // executing exit instruction address
            finish = 1;
            addr_next = addr;
        end else begin
            finish = 0;
            case (jump_addr_selection)
                2'b01: addr_next = read_data_0; // absolute jump (JR,JALR);
                2'b10: addr_next = {addr[31:28], instruction_word_prev[25:0], 2'b0}; // page absolute jump (J,JAL);
                2'b11: addr_next = (addr + {14'b0, instruction_word_prev[15:0], 2'b0}); // pc relative branch (all branch instructions);
                default: addr_next = addr + 4;
            endcase
        end
    end

    always_ff @(posedge clk) begin
        if (reset) begin
            addr <= 32'hBFC00000;
        end else if (state) begin // update PC at end of EXEC
            addr <= addr_next;
            instruction_word_prev <= instruction_word;
        end
    end

    branch_control branch_controlblock(
        .N(N),
        .Z(Z),
        .instruction_word(instruction_word),
        .state(state),
        .clk(clk),
        .B_link(B_link),
        .jump_addr_selection(jump_addr_selection)
    );
endmodule

rtl/harvard/controlpath/pc/pc_tb.v
module pc_tb();

    logic clk, state, reset, N, Z, B_link, finish;
    logic [31:0] instruction_word, addr, read_data_0;
    
    initial begin
        $dumpfile("pc_tb.vcd");
        $dumpvars(0, pc_tb);
        clk = 0;
        forever begin
            #1
            clk = !clk;
        end
    end

    logic state_next;
    assign state_next = !state;

    always_ff@(posedge clk) begin
        if(reset)
            state <= 0;
        else
            state <= state_next;
    end
    // initial begin
    //     state = 0;
    //     forever begin
    //         #2
    //         state = !state;
    //     end
    // end

    initial begin
        reset = 0;
        @(negedge clk);
        reset = 1;
        @(negedge clk);
        reset = 0;
        instruction_word = 32'b00000000011000000000000000001011; // non branch/jump 
        @(negedge clk);

        #1

        instruction_word = 0;
        N = 1;
        #4
        // bugged here!! the pc isnt jumping? cos the jump_selection is not kept long enough for branch delay slot
        instruction_word = 32'b00000100000000000000000000000010; // BLTZ offset of 8
        #4
        instruction_word = 32'b00000000011000000000000000001011; // non branch/jump 
        #4
        instruction_word = 0;
        #100;

        $finish;
    end

    pc dut(
        .clk(clk),
        .state(state),
        .reset(reset),
        .N(N),
        .Z(Z),
        .instruction_word(instruction_word),
        .read_data_0(read_data_0),
        .B_link(B_link),
        .addr(addr),
        .finish(finish)
    );
endmodule

rtl/harvard/controlpath/pc/pc_tb.vcd
$date
	Mon Nov 22 07:56:21 2021
$end
$version
	Icarus Verilog
$end
$timescale
	1s
$end
$scope module pc_tb $end
$var wire 1 ! state_next $end
$var wire 1 " finish $end
$var wire 32 # addr [31:0] $end
$var wire 1 $ B_link $end
$var reg 1 % N $end
$var reg 1 & Z $end
$var reg 1 ' clk $end
$var reg 32 ( instruction_word [31:0] $end
$var reg 32 ) read_data_0 [31:0] $end
$var reg 1 * reset $end
$var reg 1 + state $end
$scope module dut $end
$var wire 1 % N $end
$var wire 1 & Z $end
$var wire 1 ' clk $end
$var wire 32 , instruction_word [31:0] $end
$var wire 32 - read_data_0 [31:0] $end
$var wire 1 * reset $end
$var wire 1 + state $end
$var wire 2 . jump_addr_selection [1:0] $end
$var wire 1 $ B_link $end
$var reg 32 / addr [31:0] $end
$var reg 32 0 addr_next [31:0] $end
$var reg 1 " finish $end
$var reg 32 1 instruction_word_prev [31:0] $end
$scope module branch_controlblock $end
$var wire 1 % N $end
$var wire 1 & Z $end
$var wire 1 ' clk $end
$var wire 32 2 instruction_word [31:0] $end
$var wire 1 + state $end
$var reg 1 $ B_link $end
$var reg 2 3 jump_addr_selection [1:0] $end
$var reg 2 4 jump_addr_selection_next [1:0] $end
$var reg 32 5 tmp [31:0] $end
$upscope $end
$upscope $end
$upscope $end
$enddefinitions $end
#0
$dumpvars
bx 5
bx 4
bx 3
bx 2
bx 1
bx 0
bx /
bx .
bx -
bx ,
x+
0*
bx )
bx (
0'
x&
x%
x$
bx #
x"
x!
$end
#1
1'
#2
1*
0'
#3
b10111111110000000000000000000100 0
0"
1!
0+
b10111111110000000000000000000000 #
b10111111110000000000000000000000 /
1'
#4
0$
b0 4
b11000000000000000001011 (
b11000000000000000001011 ,
b11000000000000000001011 2
0*
0'
#5
b11000000000000000001011 1
0!
1+
1'
#6
0'
#7
b10111111110000000000000000001000 0
1!
0+
b10111111110000000000000000000100 #
b10111111110000000000000000000100 /
b0 5
1%
b0 (
b0 ,
b0 2
1'
#8
0'
#9
b0 1
0!
1+
1'
#10
0'
#11
b10111111110000000000000000001100 0
1!
0+
b10111111110000000000000000001000 #
b10111111110000000000000000001000 /
b11 5
b0 .
b0 3
b11 4
1'
b100000000000000000000000010 (
b100000000000000000000000010 ,
b100000000000000000000000010 2
#12
0'
#13
b100000000000000000000000010 1
0!
1+
1'
#14
0'
#15
b10111111110000000000000000010100 0
1!
0+
b10111111110000000000000000001100 #
b10111111110000000000000000001100 /
b0 5
b11 .
b11 3
b0 4
1'
b11000000000000000001011 (
b11000000000000000001011 ,
b11000000000000000001011 2
#16
0'
#17
b10111111110000000000000000111000 0
b11000000000000000001011 1
0!
1+
1'
#18
0'
#19
b10111111110000000000000000111100 0
1!
0+
b10111111110000000000000000111000 #
b10111111110000000000000000111000 /
b0 .
b0 3
1'
b0 (
b0 ,
b0 2
#20
0'
#21
b0 1
0!
1+
1'
#22
0'
#23
b10111111110000000000000001000000 0
1!
0+
b10111111110000000000000000111100 #
b10111111110000000000000000111100 /
1'
#24
0'
#25
0!
1+
1'
#26
0'
#27
b10111111110000000000000001000100 0
1!
0+
b10111111110000000000000001000000 #
b10111111110000000000000001000000 /
1'
#28
0'
#29
0!
1+
1'
#30
0'
#31
b10111111110000000000000001001000 0
1!
0+
b10111111110000000000000001000100 #
b10111111110000000000000001000100 /
1'
#32
0'
#33
0!
1+
1'
#34
0'
#35
b10111111110000000000000001001100 0
1!
0+
b10111111110000000000000001001000 #
b10111111110000000000000001001000 /
1'
#36
0'
#37
0!
1+
1'
#38
0'
#39
b10111111110000000000000001010000 0
1!
0+
b10111111110000000000000001001100 #
b10111111110000000000000001001100 /
1'
#40
0'
#41
0!
1+
1'
#42
0'
#43
b10111111110000000000000001010100 0
1!
0+
b10111111110000000000000001010000 #
b10111111110000000000000001010000 /
1'
#44
0'
#45
0!
1+
1'
#46
0'
#47
b10111111110000000000000001011000 0
1!
0+
b10111111110000000000000001010100 #
b10111111110000000000000001010100 /
1'
#48
0'
#49
0!
1+
1'
#50
0'
#51
b10111111110000000000000001011100 0
1!
0+
b10111111110000000000000001011000 #
b10111111110000000000000001011000 /
1'
#52
0'
#53
0!
1+
1'
#54
0'
#55
b10111111110000000000000001100000 0
1!
0+
b10111111110000000000000001011100 #
b10111111110000000000000001011100 /
1'
#56
0'
#57
0!
1+
1'
#58
0'
#59
b10111111110000000000000001100100 0
1!
0+
b10111111110000000000000001100000 #
b10111111110000000000000001100000 /
1'
#60
0'
#61
0!
1+
1'
#62
0'
#63
b10111111110000000000000001101000 0
1!
0+
b10111111110000000000000001100100 #
b10111111110000000000000001100100 /
1'
#64
0'
#65
0!
1+
1'
#66
0'
#67
b10111111110000000000000001101100 0
1!
0+
b10111111110000000000000001101000 #
b10111111110000000000000001101000 /
1'
#68
0'
#69
0!
1+
1'
#70
0'
#71
b10111111110000000000000001110000 0
1!
0+
b10111111110000000000000001101100 #
b10111111110000000000000001101100 /
1'
#72
0'
#73
0!
1+
1'
#74
0'
#75
b10111111110000000000000001110100 0
1!
0+
b10111111110000000000000001110000 #
b10111111110000000000000001110000 /
1'
#76
0'
#77
0!
1+
1'
#78
0'
#79
b10111111110000000000000001111000 0
1!
0+
b10111111110000000000000001110100 #
b10111111110000000000000001110100 /
1'
#80
0'
#81
0!
1+
1'
#82
0'
#83
b10111111110000000000000001111100 0
1!
0+
b10111111110000000000000001111000 #
b10111111110000000000000001111000 /
1'
#84
0'
#85
0!
1+
1'
#86
0'
#87
b10111111110000000000000010000000 0
1!
0+
b10111111110000000000000001111100 #
b10111111110000000000000001111100 /
1'
#88
0'
#89
0!
1+
1'
#90
0'
#91
b10111111110000000000000010000100 0
1!
0+
b10111111110000000000000010000000 #
b10111111110000000000000010000000 /
1'
#92
0'
#93
0!
1+
1'
#94
0'
#95
b10111111110000000000000010001000 0
1!
0+
b10111111110000000000000010000100 #
b10111111110000000000000010000100 /
1'
#96
0'
#97
0!
1+
1'
#98
0'
#99
b10111111110000000000000010001100 0
1!
0+
b10111111110000000000000010001000 #
b10111111110000000000000010001000 /
1'
#100
0'
#101
0!
1+
1'
#102
0'
#103
b10111111110000000000000010010000 0
1!
0+
b10111111110000000000000010001100 #
b10111111110000000000000010001100 /
1'
#104
0'
#105
0!
1+
1'
#106
0'
#107
b10111111110000000000000010010100 0
1!
0+
b10111111110000000000000010010000 #
b10111111110000000000000010010000 /
1'
#108
0'
#109
0!
1+
1'
#110
0'
#111
b10111111110000000000000010011000 0
1!
0+
b10111111110000000000000010010100 #
b10111111110000000000000010010100 /
1'
#112
0'
#113
0!
1+
1'
#114
0'
#115
b10111111110000000000000010011100 0
1!
0+
b10111111110000000000000010011000 #
b10111111110000000000000010011000 /
1'
#116
0'
#117
0!
1+
1'
#118
0'
#119
b10111111110000000000000010100000 0
1!
0+
b10111111110000000000000010011100 #
b10111111110000000000000010011100 /
1'
