src/datapath/regfile/regfile.v
module regfile (
	input logic clk, wen, reset,
	input logic[31:0] write_data,
	input logic[4:0] write_addr,
	input logic[4:0] read_addr_0, read_addr_1,
	output logic[31:0] read_data_0, read_data_1
);

	reg [31:0] regs [31:0];

	always_ff @(posedge clk) begin
		if(reset == 1) begin
			for(integer i = 0; i < 32; i=i+1) begin
				regs[i] <= 0;
			end
		end
		if(wen == 1) begin
			regs[write_addr] = (write_addr == 0) ? 0 : write_data;
		end
	end

	always_comb begin
		read_data_0 = (read_addr_0 == 0) ? 0 : regs[read_addr_0];
		read_data_1 = (read_addr_1 == 0) ? 0 : regs[read_addr_1];
	end

endmodule

src/datapath/regfile/regfile_tb.v
module regfile_tb ();
	
	// inputs
	logic clk, wen, reset;
	logic[31:0] write_data;
	logic[4:0] write_addr;
	logic[4:0] read_addr_0, read_addr_1;
	
	// outputs
	logic[31:0] read_data_0, read_data_1;

	// device under test
	regfile dut(
		.clk(clk), .wen(wen), .reset(reset),
		.write_data(write_data), .write_addr(write_addr),
		.read_addr_0(read_addr_0), .read_addr_1(read_addr_1),
		.read_data_0(read_data_0), .read_data_1(read_data_1)
	);

	// clk & debug waveform
	initial begin
		$dumpfile("regfile_tb.vcd");
		$dumpvars(0, regfile_tb);
		clk = 0;
		repeat(200) begin
			#2;
			clk = !clk;
		end
		$fatal(1, "Simulation ended after 100 clock cycles");
	end

	// testing
	initial begin
		wen = 0;
		reset = 0;
		write_data = 0;
		write_addr = 0;
		read_addr_0 = 0;
		read_addr_1 = 0;

		@(negedge clk);
		reset = 1;
		@(negedge clk);
		reset = 0;
		@(negedge clk);

		// WRITE TEST
		wen = 1;
		write_data = 123;
		write_addr = 3;
		read_addr_0 = 3;

		@(negedge clk);
		wen = 0;
		assert(read_data_0 == 123) else $fatal(2, "Write Failed");

		// READ TEST
		@(negedge clk);
		read_addr_1 = 3;
		@(negedge clk);
		assert(read_data_1 == 123) else $fatal(2, "Read Failed");

		// WRITE TO $zero TEST
		@(negedge clk);
		wen = 1;
		write_data = 111;
		write_addr = 0;
		read_addr_0 = 0;
		@(negedge clk);
		wen = 0;
		assert(read_data_0 == 0) else $fatal(2, "Write to $zero Failed");



		#10;
		$finish;

	end


endmodule

src/datapath/regfile/regfile_tb.vcd
$date
	Mon Nov 15 16:04:18 2021
$end
$version
	Icarus Verilog
$end
$timescale
	1s
$end
$scope module regfile_tb $end
$var wire 32 ! read_data_1 [31:0] $end
$var wire 32 " read_data_0 [31:0] $end
$var reg 1 # clk $end
$var reg 5 $ read_addr_0 [4:0] $end
$var reg 5 % read_addr_1 [4:0] $end
$var reg 1 & reset $end
$var reg 1 ' wen $end
$var reg 5 ( write_addr [4:0] $end
$var reg 32 ) write_data [31:0] $end
$scope module dut $end
$var wire 1 # clk $end
$var wire 5 * read_addr_0 [4:0] $end
$var wire 5 + read_addr_1 [4:0] $end
$var wire 1 & reset $end
$var wire 1 ' wen $end
$var wire 5 , write_addr [4:0] $end
$var wire 32 - write_data [31:0] $end
$var reg 32 . read_data_0 [31:0] $end
$var reg 32 / read_data_1 [31:0] $end
$scope begin $ivl_for_loop0 $end
$var integer 32 0 i [31:0] $end
$upscope $end
$upscope $end
$upscope $end
$enddefinitions $end
#0
$dumpvars
bx 0
b0 /
b0 .
b0 -
b0 ,
b0 +
b0 *
b0 )
b0 (
0'
0&
b0 %
b0 $
0#
b0 "
b0 !
$end
#2
1#
#4
1&
0#
#6
b100000 0
1#
#8
0&
0#
#10
1#
#12
b11 $
b11 *
b11 (
b11 ,
b1111011 )
b1111011 -
1'
0#
#14
b1111011 "
b1111011 .
1#
#16
0'
0#
#18
1#
#20
b1111011 !
b1111011 /
b11 %
b11 +
0#
#22
1#
#24
0#
#26
1#
#28
b0 "
b0 .
b0 $
b0 *
b0 (
b0 ,
b1101111 )
b1101111 -
1'
0#
#30
1#
#32
0'
0#
