rtl/bus/controlpath/pc/branch_control.v
/* 
    This module decides whether a branch/jump should be executed or not.

    There are 12 branch/jump instructions in total.

    Take note that JALR (Jump and link register) is the only link instruction that stores PC+8 in Rd instead of $31

    New control logic [1:0] jump_addr_selection is defined as such
        if 00: no jump;
        if 01: absolute jump (JR,JALR);
        if 10: page absolute jump (J,JAL);
        if 11: pc relative branch (all branch instructions);

    Written by JF
*/

module branch_control(
    input logic N, // high if rs is negative
    input logic Z, // high if rs is zero
    input logic EQ, // high if rs == rt
    input logic[31:0] instruction_word, //taking in the entire word bc of repeated branch opcodes like JALR,JR,BGEZ,BGEZAL,BLTZ,BLTZAL
    input logic state,
    input logic stall,
    input logic clk,

    output logic B_link, // high if we want the PC+8 addr to be stored in $31
    output logic [1:0] jump_addr_selection // defined above
);

    logic[1:0] jump_addr_selection_next;

    always @(*) begin
        if (!stall) begin
            case (instruction_word[31:26]) // opcodes
                0: begin
                    if (instruction_word[5:0] == 6'b001001) begin // JALR
                        jump_addr_selection_next = 2'b01; B_link = 1; // B_link is set 1 here; JALR is the only link instruction with RegDst = 1 so that rd is fed as write_addr instead of $31
                    end
                    else if (instruction_word[5:0] == 6'b001000) begin // JR
                        jump_addr_selection_next = 2'b01; B_link = 0; 
                    end
                    else begin
                        jump_addr_selection_next = 0; B_link = 0;
                    end
                end
                6'b000001: begin // special_branch_codes case
                    if (instruction_word[20:16] == 5'b00001) begin // BGEZ; branch if rs >= 0
                        jump_addr_selection_next = (!N | Z) ? 2'b11 : 0; 
                        B_link = 0;
                    end
                    else if (instruction_word[20:16] == 5'b10001) begin // BGEZAL; branch if rs >= 0
                        jump_addr_selection_next = (!N | Z) ? 2'b11 : 0; 
                        B_link = (!N | Z) ? 1 : 0;
                    end
                    else if (instruction_word[20:16] == 0) begin // BLTZ; branch if rs < 0
                        jump_addr_selection_next = (N) ? 2'b11 : 0;
                        B_link = 0;
                    end
                    else if (instruction_word[20:16] == 5'b10000) begin // BLTZAL; branch if rs < 0
                        jump_addr_selection_next = (N) ? 2'b11 : 0;
                        B_link = (N) ? 1 : 0;;
                    end
                    else begin
                        jump_addr_selection_next = 0; B_link = 0;
                    end
                end
                6'b000010: begin // J
                    jump_addr_selection_next = 2'b10; B_link = 0;
                end
                6'b000011: begin // JAL
                    jump_addr_selection_next = 2'b10; B_link = 1;
                end
                6'b000100: begin // BEQ; branch if rs==rt
                    jump_addr_selection_next = (EQ) ? 2'b11 : 0;
                    B_link = 0;
                end
                6'b000101: begin // BNE; branch if rs!=rt
                    jump_addr_selection_next = (!EQ) ? 2'b11 : 0;
                    B_link = 0;
                end
                6'b000110: begin // BLEZ; branch if rs <= 0
                    jump_addr_selection_next = (N | Z) ? 2'b11 : 0;
                    B_link = 0;
                end
                6'b000111: begin // BGTZ; branch if rs > 0
                    jump_addr_selection_next = (!N & !Z) ? 2'b11 : 0;
                    B_link = 0;
                end
                default: begin // otherwise, dont jump
                    jump_addr_selection_next = 0; B_link = 0;
                end
            endcase
            B_link = (state) ? B_link : 0; // B_link should only be high in EXEC bc its used as RegWrite
        end else begin // if stall, loop values back
            jump_addr_selection_next = jump_addr_selection;
            B_link = 0;
        end

    end

    // at every EXEC, update FF
    // delay needed so that PC only jumps after branch delay slot
    always_ff @(posedge clk) begin
        if (state) begin // update jump_addr_selection at end of EXEC (edge case is jump/branch instruction, LW (stall))
            jump_addr_selection <= jump_addr_selection_next;
        end else begin
            jump_addr_selection <= jump_addr_selection;
        end
    end
endmodule

rtl/bus/controlpath/pc/pc.v
/*
    Written by JF
*/

module pc(
    input logic clk,
    input logic state,
    input logic reset,
    input logic N, Z, EQ,
    input logic [31:0] instruction_word,
    input logic [31:0] read_data_0, // register data for JR, JALR
    input logic stall,

    output logic B_link, // bubbled up from branch_control.v so that control.v can make use of it in controlpath.v
    output logic [31:0] addr,
    output logic finish // goes high when trying to execute instruction address 0
);

    logic [31:0] addr_next, instruction_word_prev, read_data_0_prev;
    logic [1:0] jump_addr_selection; // control signal defined in branch_control.v
    
    always @(*) begin
        if(addr == 0) begin // executing exit instruction address
            finish = 1;
            addr_next = addr;
        end else if (!stall) begin // update if no stall
            finish = 0;
            case (jump_addr_selection)
                2'b01: addr_next = read_data_0_prev; // absolute jump (JR,JALR);
                2'b10: addr_next = {addr[31:28], instruction_word_prev[25:0], 2'b0}; // page absolute jump (J,JAL);
                2'b11: addr_next = (addr + {14'b0, instruction_word_prev[15:0], 2'b0}); // pc relative branch (all branch instructions);
                default: addr_next = addr + 4;
            endcase
        end else begin // if stall
            finish = 0;
            addr_next = addr;
        end
    end

    always_ff @(posedge clk) begin
        if (reset) begin
            addr <= 32'hBFC00000;
        end else if (state) begin // update PC at end of EXEC
            addr <= addr_next;
        end else begin // update at end of FETCH
            instruction_word_prev <= instruction_word;
            read_data_0_prev <= read_data_0;
        end
    end

    branch_control branch_controlblock(
        .N(N),
        .Z(Z),
        .EQ(EQ),
        .instruction_word(instruction_word),
        .state(state),
        .stall(stall),
        .clk(clk),
        .B_link(B_link),
        .jump_addr_selection(jump_addr_selection)
    );
endmodule

rtl/bus/controlpath/pc/pc_tb.v
/*
    Written by JF

    Branch delay slot, B_link results, jumps as expected
*/
module pc_tb();

    logic clk, state, reset, N, Z, B_link, finish, stall, EQ;
    logic [31:0] instruction_word, addr, read_data_0;
    integer testcase;
    
    initial begin
        $dumpfile("pc_tb.vcd");
        $dumpvars(0, pc_tb);
        clk = 0;
        forever begin
            #1
            clk = !clk;
        end
    end

    logic state_next;
    assign state_next = (stall) ? state : !state;

    always_ff@(posedge clk) begin
        if(reset)
            state <= 0;
        else begin
            state <= state_next;
        end
    end
    // initial begin
    //     state = 0;
    //     forever begin
    //         #2
    //         state = !state;
    //     end
    // end

    initial begin
        $monitor("Test case: %d,State: %b, Stall: %b, instruction_word: %h, addr: %h",testcase,state,stall,instruction_word,addr);
        reset = 0;
        stall = 0;
        @(posedge clk);
        reset = 1;
        @(negedge clk);
        reset = 0;
        instruction_word = 32'h0060000b; // non branch/jump 
        @(posedge clk);

        @(posedge state);

        instruction_word = 0;
        @(posedge state);

        //test case of BLTZ offset of 8 w/ condition fulfilled
        testcase = 0;
        N = 1;
        instruction_word = 32'h04000002; // BLTZ offset of 8
        @(posedge state);
        stall = 1;
        @(negedge clk);
        @(posedge clk);
        stall = 0;
        instruction_word = 32'h0060000b; // non branch/jump 
        @(posedge state);
        // #4
        instruction_word = 0; // non branch/jump
        @(posedge state);
        // #4 

        //test case of BLTZ offset of 8 w/ condition not fulfilled
        testcase = 1;
        N = 0;
        instruction_word = 32'h04000002; // BLTZ offset of 8
        @(posedge state);
        instruction_word = 32'h0060000b; // non branch/jump 
        @(posedge state);
        instruction_word = 0; // non branch/jump
        @(posedge state);
        stall = 1;
        instruction_word = 32'h04110002; // BGEZAL offset of 8 
        @(negedge clk);
        @(posedge clk);
        @(negedge clk);
        @(posedge clk);
        stall = 0;
        // test case of BGEZAL offset of 8 w/ condition fulfilled
        testcase = 2;
        N = 0; Z = 1;
        @(negedge state);
        stall = 1;
        @(negedge clk);
        @(posedge clk);
        stall = 0;
        @(posedge state); 
        stall = 1;
        instruction_word = 32'h0060000b; // non branch/jump 
        @(negedge clk);
        @(posedge clk);
        @(negedge clk);
        @(posedge clk);
        stall = 0;
        @(negedge state);
        stall = 1;
        @(negedge clk);
        @(posedge clk);
        stall = 0;
        @(posedge state); 
        instruction_word = 0; // non branch/jump
        @(posedge state);

        // test case of BGEZAL offset of 8 w/ condition unfulfilled
        testcase = 3;
        N = 1; Z = 0;
        instruction_word = 32'h04110002; // BGEZAL offset of 8 
        @(posedge state);
        instruction_word = 32'h0060000b; // non branch/jump 
        @(posedge state);
        instruction_word = 0; // non branch/jump
        @(posedge state);

        // test case of JAL, page jump to 0b0000000000000000000000000100;
        testcase = 4;
        // N = 1; Z = 0;
        instruction_word = 32'h0c000001; // JAL, page jump to 0b0000000000000000000000000100;
        @(posedge state);
        instruction_word = 32'h0060000b; // non branch/jump 
        @(posedge state);
        instruction_word = 0; // non branch/jump
        @(posedge state);

        // test case of JALR, absolute jump to 0b1;
        testcase = 5;
        // N = 1; Z = 0;
        read_data_0 = 1;
        instruction_word = 32'h00000009; // JALR, absolute jump to 0b1;
        @(posedge state);
        instruction_word = 32'h0060000b; // non branch/jump 
        @(posedge state);
        instruction_word = 0; // non branch/jump
        @(posedge state);

        #100;

        $finish;
    end

    pc dut(
        .clk(clk),
        .state(state),
        .reset(reset),
        .N(N),
        .EQ(EQ),
        .stall(stall),
        .Z(Z),
        .instruction_word(instruction_word),
        .read_data_0(read_data_0),
        .B_link(B_link),
        .addr(addr),
        .finish(finish)
    );
endmodule

rtl/bus/controlpath/pc/pc_tb.vcd
$date
	Wed Dec  1 22:59:31 2021
$end
$version
	Icarus Verilog
$end
$timescale
	1s
$end
$scope module pc_tb $end
$var wire 1 ! state_next $end
$var wire 1 " finish $end
$var wire 32 # addr [31:0] $end
$var wire 1 $ B_link $end
$var reg 1 % EQ $end
$var reg 1 & N $end
$var reg 1 ' Z $end
$var reg 1 ( clk $end
$var reg 32 ) instruction_word [31:0] $end
$var reg 32 * read_data_0 [31:0] $end
$var reg 1 + reset $end
$var reg 1 , stall $end
$var reg 1 - state $end
$var integer 32 . testcase [31:0] $end
$scope module dut $end
$var wire 1 % EQ $end
$var wire 1 & N $end
$var wire 1 ' Z $end
$var wire 1 ( clk $end
$var wire 32 / instruction_word [31:0] $end
$var wire 32 0 read_data_0 [31:0] $end
$var wire 1 + reset $end
$var wire 1 , stall $end
$var wire 1 - state $end
$var wire 2 1 jump_addr_selection [1:0] $end
$var wire 1 $ B_link $end
$var reg 32 2 addr [31:0] $end
$var reg 32 3 addr_next [31:0] $end
$var reg 1 " finish $end
$var reg 32 4 instruction_word_prev [31:0] $end
$var reg 32 5 read_data_0_prev [31:0] $end
$scope module branch_controlblock $end
$var wire 1 % EQ $end
$var wire 1 & N $end
$var wire 1 ' Z $end
$var wire 1 ( clk $end
$var wire 32 6 instruction_word [31:0] $end
$var wire 1 , stall $end
$var wire 1 - state $end
$var reg 1 $ B_link $end
$var reg 2 7 jump_addr_selection [1:0] $end
$var reg 2 8 jump_addr_selection_next [1:0] $end
$upscope $end
$upscope $end
$upscope $end
$enddefinitions $end
#0
$dumpvars
b0 8
bx 7
bx 6
bx 5
bx 4
bx 3
bx 2
bx 1
bx 0
bx /
bx .
x-
0,
0+
bx *
bx )
0(
x'
x&
x%
0$
bx #
0"
x!
$end
#1
b10111111110000000000000000000100 3
1!
b10111111110000000000000000000000 #
b10111111110000000000000000000000 2
0-
1+
1(
#2
b11000000000000000001011 )
b11000000000000000001011 /
b11000000000000000001011 6
0+
0(
#3
0!
b0 )
b0 /
b0 6
1-
b11000000000000000001011 4
1(
#4
0(
#5
b10111111110000000000000000001000 3
1!
b0 1
b0 7
b10111111110000000000000000000100 #
b10111111110000000000000000000100 2
0-
1(
#6
0(
#7
0!
b11 8
b100000000000000000000000010 )
b100000000000000000000000010 /
b100000000000000000000000010 6
1&
b0 .
1-
b0 4
1(
#8
0(
#9
1!
b11 1
b11 7
b10111111110000000000000000001000 #
b10111111110000000000000000001000 2
0-
1(
#10
0(
#11
1,
b10111111110000000000000000001000 3
1-
b100000000000000000000000010 4
1(
#12
0(
#13
0!
b0 8
b10111111110000000000000000010000 3
b11000000000000000001011 )
b11000000000000000001011 /
b11000000000000000001011 6
0,
1(
#14
0(
#15
1!
b10111111110000000000000000010100 3
0-
b10111111110000000000000000010000 #
b10111111110000000000000000010000 2
b0 1
b0 7
1(
#16
0(
#17
0!
b0 )
b0 /
b0 6
b11000000000000000001011 4
1-
1(
#18
0(
#19
1!
b10111111110000000000000000011000 3
0-
b10111111110000000000000000010100 #
b10111111110000000000000000010100 2
1(
#20
0(
#21
0!
b100000000000000000000000010 )
b100000000000000000000000010 /
b100000000000000000000000010 6
0&
b1 .
b0 4
1-
1(
#22
0(
#23
1!
b10111111110000000000000000011100 3
0-
b10111111110000000000000000011000 #
b10111111110000000000000000011000 2
1(
#24
0(
#25
0!
b11000000000000000001011 )
b11000000000000000001011 /
b11000000000000000001011 6
b100000000000000000000000010 4
1-
1(
#26
0(
#27
1!
b10111111110000000000000000100000 3
0-
b10111111110000000000000000011100 #
b10111111110000000000000000011100 2
1(
#28
0(
#29
0!
b0 )
b0 /
b0 6
b11000000000000000001011 4
1-
1(
#30
0(
#31
1!
b10111111110000000000000000100100 3
0-
b10111111110000000000000000100000 #
b10111111110000000000000000100000 2
1(
#32
0(
#33
b10111111110000000000000000100000 3
b100000100010000000000000010 )
b100000100010000000000000010 /
b100000100010000000000000010 6
1,
b0 4
1-
1(
#34
0(
#35
1(
#36
0(
#37
0!
1$
b11 8
b10111111110000000000000000100100 3
1'
b10 .
0,
1(
#38
0(
#39
1,
0$
0-
b10111111110000000000000000100100 #
b10111111110000000000000000100100 2
b11 1
b11 7
1(
#40
0(
#41
b10111111110000000000000000101100 3
b100000100010000000000000010 4
1!
0$
0,
1(
#42
0(
#43
b10111111110000000000000000100100 3
b11000000000000000001011 )
b11000000000000000001011 /
b11000000000000000001011 6
1,
1-
1(
#44
0(
#45
1(
#46
0(
#47
0!
b0 8
b10111111110000000000000000101100 3
0,
1(
#48
0(
#49
1,
b0 1
b0 7
b10111111110000000000000000101100 #
b10111111110000000000000000101100 2
0-
1(
#50
0(
#51
b11000000000000000001011 4
1!
b10111111110000000000000000110000 3
0,
1(
#52
0(
#53
0!
b0 )
b0 /
b0 6
1-
1(
#54
0(
#55
1!
b10111111110000000000000000110100 3
0-
b10111111110000000000000000110000 #
b10111111110000000000000000110000 2
1(
#56
0(
#57
0!
b100000100010000000000000010 )
b100000100010000000000000010 /
b100000100010000000000000010 6
0'
1&
b11 .
b0 4
1-
1(
#58
0(
#59
1!
b10111111110000000000000000111000 3
0-
b10111111110000000000000000110100 #
b10111111110000000000000000110100 2
1(
#60
0(
#61
0!
b11000000000000000001011 )
b11000000000000000001011 /
b11000000000000000001011 6
b100000100010000000000000010 4
1-
1(
#62
0(
#63
1!
b10111111110000000000000000111100 3
0-
b10111111110000000000000000111000 #
b10111111110000000000000000111000 2
1(
#64
0(
#65
0!
b0 )
b0 /
b0 6
b11000000000000000001011 4
1-
1(
#66
0(
#67
1!
b10111111110000000000000001000000 3
0-
b10111111110000000000000000111100 #
b10111111110000000000000000111100 2
1(
#68
0(
#69
0!
1$
b10 8
b1100000000000000000000000001 )
b1100000000000000000000000001 /
b1100000000000000000000000001 6
b100 .
b0 4
1-
1(
#70
0(
#71
1!
0$
b10110000000000000000000000000000 3
0-
b10111111110000000000000001000000 #
b10111111110000000000000001000000 2
b10 1
b10 7
1(
#72
0(
#73
b10110000000000000000000000000100 3
0!
b0 8
b11000000000000000001011 )
b11000000000000000001011 /
b11000000000000000001011 6
b1100000000000000000000000001 4
1-
1(
#74
0(
#75
1!
b10110000000000000000000000001000 3
0-
b10110000000000000000000000000100 #
b10110000000000000000000000000100 2
b0 1
b0 7
1(
#76
0(
#77
0!
b0 )
b0 /
b0 6
b11000000000000000001011 4
1-
1(
#78
0(
#79
1!
b10110000000000000000000000001100 3
0-
b10110000000000000000000000001000 #
b10110000000000000000000000001000 2
1(
#80
0(
#81
0!
1$
b1 8
b1001 )
b1001 /
b1001 6
b1 *
b1 0
b101 .
b0 4
1-
1(
#82
0(
#83
1!
0$
bx 3
0-
b10110000000000000000000000001100 #
b10110000000000000000000000001100 2
b1 1
b1 7
1(
#84
0(
#85
b1 3
0!
b0 8
b11000000000000000001011 )
b11000000000000000001011 /
b11000000000000000001011 6
b1 5
b1001 4
1-
1(
#86
0(
#87
1!
b101 3
0-
b1 #
b1 2
b0 1
b0 7
1(
#88
0(
#89
0!
b0 )
b0 /
b0 6
b11000000000000000001011 4
1-
1(
#90
0(
#91
1!
b1001 3
0-
b101 #
b101 2
1(
#92
0(
#93
0!
b0 4
1-
1(
#94
0(
#95
1!
b1101 3
0-
b1001 #
b1001 2
1(
#96
0(
#97
0!
1-
1(
#98
0(
#99
1!
b10001 3
0-
b1101 #
b1101 2
1(
#100
0(
#101
0!
1-
1(
#102
0(
#103
1!
b10101 3
0-
b10001 #
b10001 2
1(
#104
0(
#105
0!
1-
1(
#106
0(
#107
1!
b11001 3
0-
b10101 #
b10101 2
1(
#108
0(
#109
0!
1-
1(
#110
0(
#111
1!
b11101 3
0-
b11001 #
b11001 2
1(
#112
0(
#113
0!
1-
1(
#114
0(
#115
1!
b100001 3
0-
b11101 #
b11101 2
1(
#116
0(
#117
0!
1-
1(
#118
0(
#119
1!
b100101 3
0-
b100001 #
b100001 2
1(
#120
0(
#121
0!
1-
1(
#122
0(
#123
1!
b101001 3
0-
b100101 #
b100101 2
1(
#124
0(
#125
0!
1-
1(
#126
0(
#127
1!
b101101 3
0-
b101001 #
b101001 2
1(
#128
0(
#129
0!
1-
1(
#130
0(
#131
1!
b110001 3
0-
b101101 #
b101101 2
1(
#132
0(
#133
0!
1-
1(
#134
0(
#135
1!
b110101 3
0-
b110001 #
b110001 2
1(
#136
0(
#137
0!
1-
1(
#138
0(
#139
1!
b111001 3
0-
b110101 #
b110101 2
1(
#140
0(
#141
0!
1-
1(
#142
0(
#143
1!
b111101 3
0-
b111001 #
b111001 2
1(
#144
0(
#145
0!
1-
1(
#146
0(
#147
1!
b1000001 3
0-
b111101 #
b111101 2
1(
#148
0(
#149
0!
1-
1(
#150
0(
#151
1!
b1000101 3
0-
b1000001 #
b1000001 2
1(
#152
0(
#153
0!
1-
1(
#154
0(
#155
1!
b1001001 3
0-
b1000101 #
b1000101 2
1(
#156
0(
#157
0!
1-
1(
#158
0(
#159
1!
b1001101 3
0-
b1001001 #
b1001001 2
1(
#160
0(
#161
0!
1-
1(
#162
0(
#163
1!
b1010001 3
0-
b1001101 #
b1001101 2
1(
#164
0(
#165
0!
1-
1(
#166
0(
#167
1!
b1010101 3
0-
b1010001 #
b1010001 2
1(
#168
0(
#169
0!
1-
1(
#170
0(
#171
1!
b1011001 3
0-
b1010101 #
b1010101 2
1(
#172
0(
#173
0!
1-
1(
#174
0(
#175
1!
b1011101 3
0-
b1011001 #
b1011001 2
1(
#176
0(
#177
0!
1-
1(
#178
0(
#179
1!
b1100001 3
0-
b1011101 #
b1011101 2
1(
#180
0(
#181
0!
1-
1(
#182
0(
#183
1!
b1100101 3
0-
b1100001 #
b1100001 2
1(
#184
0(
#185
0!
1-
1(
#186
0(
#187
1!
b1101001 3
0-
b1100101 #
b1100101 2
1(
#188
0(
#189
0!
1-
1(
#190
0(
#191
1!
b1101101 3
0-
b1101001 #
b1101001 2
1(
#192
0(
#193
0!
1-
1(
